examples/dump.py
examples/formatable.py
examples/printable.py
examples/printer.py
nicely/__init__.py
nicely/formatters.py
nicely/printer.py
nicely/utils.py
nicely-0.2542.0.dist-info/METADATA
nicely-0.2542.0.dist-info/WHEEL
nicely-0.2542.0.dist-info/top_level.txt
nicely-0.2542.0.dist-info/RECORD
