Metadata-Version: 2.4
Name: nicely
Version: 0.2542.0
Summary: Python Fancy Printer
Author-email: Louis RIVIERE <louis@riviere.xyz>
License: MIT
Project-URL: pypi, https://pypi.org/project/nicely
Project-URL: repository, https://framagit.org/louis-riviere-xyz/nicely/tree/stable
Keywords: util
Classifier: Development Status :: 4 - Beta
Classifier: License :: OSI Approved :: MIT License
Classifier: Programming Language :: Python :: 3
Classifier: Operating System :: POSIX :: Linux
Classifier: Environment :: Console
Classifier: Intended Audience :: Developers
Requires-Python: >=3.12
Provides-Extra: dev
Requires-Dist: pytest; extra == "dev"
